adc132/__init__.py
adc132/main.py
adc132-0.1.0.dist-info/METADATA
adc132-0.1.0.dist-info/WHEEL
adc132-0.1.0.dist-info/RECORD
